picai_prep/__init__.py
picai_prep/__main__.py
picai_prep/converter.py
picai_prep/data_utils.py
picai_prep/dcm2dce.py
picai_prep/dcm2mha.py
picai_prep/errors.py
picai_prep/mha2nnunet.py
picai_prep/nnunet2nndet.py
picai_prep/preprocessing.py
picai_prep/py.typed
picai_prep/utilities.py
picai_prep/examples/__init__.py
picai_prep/examples/dcm2mha/__init__.py
picai_prep/examples/dcm2mha/sample_archive.py
picai_prep/examples/mha2nnunet/__init__.py
picai_prep/examples/mha2nnunet/picai_archive.py
picai_prep/examples/mha2nnunet/picai_archive_inference.py
picai_prep/examples/mha2nnunet/picai_archive_search.py
picai_prep/examples/mha2nnunet/sample_archive.py
picai_prep/examples/mha2nnunet/sample_archive_inference.py
picai_prep/resources/__init__.py
picai_prep/resources/dcm2mha_schema.py
picai_prep/resources/dicom_tags.py
picai_prep/resources/mha2nnunet_schema.py
picai_prep-2.1.13.dist-info/licenses/LICENSE
picai_prep-2.1.13.dist-info/METADATA
picai_prep-2.1.13.dist-info/WHEEL
picai_prep-2.1.13.dist-info/top_level.txt
picai_prep-2.1.13.dist-info/RECORD
