Metadata-Version: 2.4
Name: picai_prep
Version: 2.1.13
Summary: PICAI Preprocessing
Home-page: https://github.com/DIAGNijmegen/picai_prep
Author: Joeran Bosma, Stan Noordman, Anindo Saha and Matin Hosseinzadeh
Author-email: Joeran.Bosma@radboudumc.nl
License: Apache License, Version 2.0
Project-URL: Bug Tracker, https://github.com/DIAGNijmegen/picai_prep/issues
Platform: unix
Platform: linux
Platform: osx
Platform: cygwin
Platform: win32
Classifier: Programming Language :: Python :: 3
Classifier: Programming Language :: Python :: 3 :: Only
Classifier: Programming Language :: Python :: 3.7
Classifier: Programming Language :: Python :: 3.8
Classifier: Programming Language :: Python :: 3.9
Classifier: Programming Language :: Python :: 3.10
Requires-Python: >=3.7
License-File: LICENSE
Requires-Dist: dataclasses
Requires-Dist: jsonschema
Requires-Dist: numpy
Requires-Dist: pydicom
Requires-Dist: scikit-image
Requires-Dist: scikit-learn
Requires-Dist: scipy
Requires-Dist: SimpleITK
Requires-Dist: tqdm
Provides-Extra: testing
Requires-Dist: pytest>=6.0; extra == "testing"
Requires-Dist: pytest-cov>=2.0; extra == "testing"
Requires-Dist: mypy>=0.910; extra == "testing"
Requires-Dist: flake8>=3.9; extra == "testing"
Requires-Dist: tox>=3.24; extra == "testing"
Dynamic: author-email
Dynamic: description
Dynamic: description-content-type
Dynamic: home-page
Dynamic: license
Dynamic: license-file
Dynamic: project-url
